spamdetection/SpamDetector.py
spamdetection/__init__.py
spamdetection/__main__.py
spamdetection/app.py
spamdetection/params.py
spamdetection/Model/sms_model_v1.pkl
spamdetection-0.0.9.dist-info/METADATA
spamdetection-0.0.9.dist-info/WHEEL
spamdetection-0.0.9.dist-info/entry_points.txt
spamdetection-0.0.9.dist-info/top_level.txt
spamdetection-0.0.9.dist-info/RECORD
