Metadata-Version: 2.1
Name: spamdetection
Version: 0.0.9
Summary: Classify text messages between 'spam' and 'ham'
Home-page: https://github.com/fabio-a-oliveira/nuveo-teste-ia
Author: Fabio Oliveira
Author-email: fabio.afdo@gmail.com
License: MIT
Platform: UNKNOWN
Classifier: License :: OSI Approved :: MIT License
Classifier: Programming Language :: Python :: 3
Classifier: Programming Language :: Python :: 3.8
Requires-Dist: scikit-learn (>=0.24.1)
Requires-Dist: pywebio (>=1.3.2)
